{
	"name": "ds_dl_silver_Customers_in",
	"properties": {
		"linkedServiceName": {
			"referenceName": "ls_myFirstProj_DLake_output",
			"type": "LinkedServiceReference"
		},
		"folder": {
			"name": "ADE Classes/myFirstProject"
		},
		"annotations": [],
		"type": "Parquet",
		"typeProperties": {
			"location": {
				"type": "AzureBlobFSLocation",
				"folderPath": "customerorders/customers",
				"fileSystem": "silver"
			},
			"compressionCodec": "snappy"
		},
		"schema": [
			{
				"name": "CUSTOMER_ID",
				"type": "INT32"
			},
			{
				"name": "FULL_NAME",
				"type": "UTF8"
			},
			{
				"name": "EMAIL_ADDRESS",
				"type": "UTF8"
			},
			{
				"name": "Ingestion_by",
				"type": "UTF8"
			},
			{
				"name": "Ingestion_TimeStamp",
				"type": "UTF8"
			},
			{
				"name": "Ingestion_Date",
				"type": "UTF8"
			},
			{
				"name": "IngestedBy",
				"type": "UTF8"
			}
		]
	},
	"type": "Microsoft.DataFactory/factories/datasets"
}